{
  "universalBlueprintVersion": "1.0",
  "universalBlueprintEnabled": true,
  "contractId": "readiness-audit-saas-crm-1782833348329",
  "ideaId": "idea-1",
  "appName": "CRM",
  "generatedAt": "2026-06-30T15:29:08.522Z",
  "defaultSections": [
    "launch",
    "welcome",
    "auth",
    "onboarding",
    "shell",
    "home",
    "search",
    "notifications",
    "profile",
    "settings",
    "help",
    "feedback",
    "legal",
    "analytics",
    "security",
    "monetization",
    "universal-ai"
  ]
}
